brodoso_test/__init__.py
brodoso_test/test.py
brodoso_test-7.0.0.dist-info/LICENSE.txt
brodoso_test-7.0.0.dist-info/METADATA
brodoso_test-7.0.0.dist-info/WHEEL
brodoso_test-7.0.0.dist-info/top_level.txt
brodoso_test-7.0.0.dist-info/RECORD
