Metadata-Version: 2.1
Name: brodoso-test
Version: 7.0.0
Summary: Python runtime for DHCore
Author-email: carlo <carlo@test.eu>
License:                               Apache License
Keywords: test
Classifier: License :: OSI Approved :: Apache Software License
Classifier: Programming Language :: Python :: 3.9
Classifier: Programming Language :: Python :: 3.10
Classifier: Programming Language :: Python :: 3.11
Requires-Python: >=3.9
License-File: LICENSE.txt
